Tnail-0.1.dist-info/METADATA
Tnail-0.1.dist-info/RECORD
Tnail-0.1.dist-info/WHEEL
Tnail-0.1.dist-info/top_level.txt
thumbnail/__init__.py
thumbnail/thumbnail.py
tnail/__init__.py
tnail/tnail.py
